{
    "printer": {
        "@id": "printer/Epson-Stylus_Photo_790",
        "make": "Epson",
        "model": "Stylus Photo 790",
        "mechanism": {
            "inkjet": null,
            "color": null,
            "resolution": {
                "dpi": {
                    "x": "2880",
                    "y": "720"
                }
            }
        },
        "lang": {
            "escp": null,
            "text": {
                "charset": "us-ascii"
            }
        },
        "autodetect": {
            "usb": {
                "commandset": "ESCPL2,BDC,D4",
                "description": "EPSON Stylus Photo 790",
                "manufacturer": "EPSON",
                "model": "Stylus Photo 790"
            }
        },
        "functionality": "A",
        "driver": "gutenprint",
        "comments": {
            "en": "Probably the smae printer as the Stylus Photo 780.<p>\n    6-color CMYKcm printing.<br>\n    USB or Parallel."
        }
    }
}