{
    "printer": {
        "@id": "printer/Epson-ME_82WD_Series",
        "make": "Epson",
        "model": "ME 82WD Series",
        "mechanism": {
            "inkjet": null,
            "color": null,
            "resolution": {
                "dpi": {
                    "x": "5760",
                    "y": "1440"
                }
            }
        },
        "url": "http://www.epson.com/",
        "autodetect": {
            "general": {
                "ieee1284": "MFG:EPSON;CMD:ESCPL2,BDC,D4,D4PX,ESCPR2;MDL:Epson ME OFFICE 82WD;CLS:PRINTER;DES:EPSON Epson ME OFFICE 82WD",
                "commandset": "ESCPL2,BDC,D4,D4PX,ESCPR2",
                "description": "EPSON Epson ME OFFICE 82WD",
                "manufacturer": "EPSON",
                "model": "Epson ME OFFICE 82WD"
            }
        },
        "functionality": "A",
        "driver": "epson-workforce-635-60-nx625-series",
        "drivers": {
            "driver": {
                "id": "epson-workforce-635-60-nx625-series"
            }
        },
        "comments": {
            "en": "All-in-One color inkjet printer.<p>\n      Maximum paper width: 21.0 cm / 8.3 inches<p>"
        }
    }
}